pytest_reporter/__init__.py
pytest_reporter/hooks.py
pytest_reporter/plugin.py
pytest_reporter-0.5.2.dist-info/LICENSE
pytest_reporter-0.5.2.dist-info/METADATA
pytest_reporter-0.5.2.dist-info/WHEEL
pytest_reporter-0.5.2.dist-info/entry_points.txt
pytest_reporter-0.5.2.dist-info/top_level.txt
pytest_reporter-0.5.2.dist-info/RECORD
