Metadata-Version: 1.2
Name: pytest-reporter
Version: 0.5.2
Summary: Generate Pytest reports with templates
Home-page: https://github.com/christiansandberg/pytest-reporter
Author: Christian Sandberg
Author-email: christiansandberg@me.com
Maintainer: Christian Sandberg
Maintainer-email: christiansandberg@me.com
License: MIT
Platform: UNKNOWN
Classifier: Development Status :: 4 - Beta
Classifier: Framework :: Pytest
Classifier: Intended Audience :: Developers
Classifier: Topic :: Software Development :: Testing
Classifier: Programming Language :: Python
Classifier: Operating System :: OS Independent
Classifier: License :: OSI Approved :: MIT License
Requires-Python: >=3.5
